MANIFEST.in
PROJECT.rst
README.md
setup.py
Carillon.egg-info/PKG-INFO
Carillon.egg-info/SOURCES.txt
Carillon.egg-info/dependency_links.txt
Carillon.egg-info/entry_points.txt
Carillon.egg-info/requires.txt
Carillon.egg-info/top_level.txt
carillon/__init__.py
carillon/__main__.py
carillon/default.yml
carillon/icons/ac.png
carillon/icons/ad.png
carillon/icons/ae.png
carillon/icons/af.png
carillon/icons/ag.png
carillon/icons/ai.png
carillon/icons/al.png
carillon/icons/am.png
carillon/icons/an.png
carillon/icons/ao.png
carillon/icons/aq.png
carillon/icons/ar.png
carillon/icons/as.png
carillon/icons/at.png
carillon/icons/au.png
carillon/icons/aw.png
carillon/icons/ax.png
carillon/icons/az.png
carillon/icons/ba.png
carillon/icons/bb.png
carillon/icons/bd.png
carillon/icons/be.png
carillon/icons/bf.png
carillon/icons/bg.png
carillon/icons/bh.png
carillon/icons/bi.png
carillon/icons/bj.png
carillon/icons/bl.png
carillon/icons/bm.png
carillon/icons/bn.png
carillon/icons/bo.png
carillon/icons/bq.png
carillon/icons/br.png
carillon/icons/bs.png
carillon/icons/bt.png
carillon/icons/bv.png
carillon/icons/bw.png
carillon/icons/by.png
carillon/icons/bz.png
carillon/icons/ca.png
carillon/icons/cat.png
carillon/icons/cc.png
carillon/icons/cd.png
carillon/icons/cf.png
carillon/icons/cg.png
carillon/icons/ch.png
carillon/icons/ci.png
carillon/icons/ck.png
carillon/icons/cl.png
carillon/icons/cm.png
carillon/icons/cn.png
carillon/icons/co.png
carillon/icons/cr.png
carillon/icons/cs.png
carillon/icons/cu.png
carillon/icons/cv.png
carillon/icons/cw.png
carillon/icons/cx.png
carillon/icons/cy.png
carillon/icons/cz.png
carillon/icons/dd.png
carillon/icons/de.png
carillon/icons/dj.png
carillon/icons/dk.png
carillon/icons/dm.png
carillon/icons/do.png
carillon/icons/dz.png
carillon/icons/ec.png
carillon/icons/ee.png
carillon/icons/eg.png
carillon/icons/eh.png
carillon/icons/er.png
carillon/icons/es.png
carillon/icons/et.png
carillon/icons/eu.png
carillon/icons/fi.png
carillon/icons/fj.png
carillon/icons/fk.png
carillon/icons/fm.png
carillon/icons/fo.png
carillon/icons/fr.png
carillon/icons/fx.png
carillon/icons/ga.png
carillon/icons/gb.png
carillon/icons/gd.png
carillon/icons/ge.png
