Metadata-Version: 1.2
Name: Carillon
Version: 1.0.2
Summary: Ultra simple keyboard layout controller
Home-page: https://github.com/sbreatnach/carillon
Author: Shane Breatnach
Author-email: shane.breatnach@gmail.com
License: MIT
Download-URL: https://github.com/sbreatnach/carillon/archive/1.0.2.tar.gz
Keywords: carillon setxkbmap keyboard keyboards layout linux openbox
Platform: UNKNOWN
Classifier: Development Status :: 3 - Alpha
Classifier: Intended Audience :: Developers
Classifier: License :: OSI Approved :: MIT License
Classifier: Programming Language :: Python :: 2
Classifier: Programming Language :: Python :: 2.7
Classifier: Programming Language :: Python :: 3
Classifier: Programming Language :: Python :: 3.4
Classifier: Programming Language :: Python :: 3.5
Classifier: Programming Language :: Python :: 3.6
Requires-Python: ~=3.3
